{
  "influencers": [
    {
      "id": "mock-1",
      "handle": "@prettyliv",
      "platform": "instagram",
      "full_name": "Liv Santos",
      "email": "liv@example.com",
      "follower_count": "245000",
      "engagement_rate": "3.2",
      "niche": "Beauty",
      "contact_status": "contacted",
      "stage": "2",
      "outreach_method": "dm",
      "agreed_rate": "500",
      "notes": "Very responsive. Great engagement with audience.",
      "custom": {}
    },
    {
      "id": "mock-2",
      "handle": "@fitwithjay",
      "platform": "tiktok",
      "full_name": "Jay Kim",
      "email": "jay@example.com",
      "follower_count": "890000",
      "engagement_rate": "5.8",
      "niche": "Fitness",
      "contact_status": "interested",
      "stage": "3",
      "outreach_method": "email",
      "agreed_rate": "1200",
      "notes": "Discussing deliverables for Q1 campaign. Very enthusiastic.",
      "custom": {}
    },
    {
      "id": "mock-3",
      "handle": "@travelwithmar",
      "platform": "youtube",
      "full_name": "Marco Reyes",
      "email": "marco@example.com",
      "follower_count": "1200000",
      "engagement_rate": "2.1",
      "niche": "Travel",
      "contact_status": "agreed",
      "stage": "4",
      "outreach_method": "email",
      "agreed_rate": "2500",
      "notes": "Contract signed for summer campaign. Content scheduled for June.",
      "custom": {}
    },
    {
      "id": "mock-4",
      "handle": "@techsavvy",
      "platform": "twitter",
      "full_name": "Alex Chen",
      "email": "alex@example.com",
      "follower_count": "45000",
      "engagement_rate": "4.5",
      "niche": "Technology",
      "contact_status": "not_contacted",
      "stage": "1",
      "outreach_method": "",
      "agreed_rate": "",
      "notes": "Potential for product review. Tech gadgets focus.",
      "custom": {}
    },
    {
      "id": "mock-5",
      "handle": "@foodie.emma",
      "platform": "instagram",
      "full_name": "Emma Rodriguez",
      "email": "emma@foodie.com",
      "follower_count": "567000",
      "engagement_rate": "4.2",
      "niche": "Food",
      "contact_status": "contacted",
      "stage": "2",
      "outreach_method": "dm",
      "agreed_rate": "800",
      "notes": "Specializes in vegan recipes. High engagement on reels.",
      "custom": {}
    },
    {
      "id": "mock-6",
      "handle": "@gymtom",
      "platform": "tiktok",
      "full_name": "Tom Harrison",
      "email": "tom@gymlife.com",
      "follower_count": "1250000",
      "engagement_rate": "6.3",
      "niche": "Fitness",
      "contact_status": "interested",
      "stage": "3",
      "outreach_method": "email",
      "agreed_rate": "1800",
      "notes": "Workout influencer. Great for supplement campaign.",
      "custom": {}
    },
    {
      "id": "mock-7",
      "handle": "@fashionista",
      "platform": "instagram",
      "full_name": "Sophia Lee",
      "email": "sophia@fashion.com",
      "follower_count": "890000",
      "engagement_rate": "3.8",
      "niche": "Fashion",
      "contact_status": "agreed",
      "stage": "4",
      "outreach_method": "email",
      "agreed_rate": "1500",
      "notes": "Signed for spring collection campaign.",
      "custom": {}
    },
    {
      "id": "mock-8",
      "handle": "@momlife_jess",
      "platform": "instagram",
      "full_name": "Jessica Martin",
      "email": "jess@momlife.com",
      "follower_count": "234000",
      "engagement_rate": "5.1",
      "niche": "Parenting",
      "contact_status": "contacted",
      "stage": "2",
      "outreach_method": "dm",
      "agreed_rate": "450",
      "notes": "Family content creator. Good for baby products.",
      "custom": {}
    },
    {
      "id": "mock-9",
      "handle": "@petlover_ali",
      "platform": "tiktok",
      "full_name": "Ali Hassan",
      "email": "ali@pets.com",
      "follower_count": "678000",
      "engagement_rate": "7.2",
      "niche": "Pets",
      "contact_status": "interested",
      "stage": "2",
      "outreach_method": "dm",
      "agreed_rate": "900",
      "notes": "Dog training content. Viral videos frequently.",
      "custom": {}
    },
    {
      "id": "mock-10",
      "handle": "@makeup_mia",
      "platform": "youtube",
      "full_name": "Mia Williams",
      "email": "mia@makeup.com",
      "follower_count": "450000",
      "engagement_rate": "4.7",
      "niche": "Beauty",
      "contact_status": "not_contacted",
      "stage": "1",
      "outreach_method": "",
      "agreed_rate": "",
      "notes": "Tutorials and reviews. Good for cosmetics.",
      "custom": {}
    },
    {
      "id": "mock-11",
      "handle": "@adventure_max",
      "platform": "instagram",
      "full_name": "Max Thompson",
      "email": "max@adventure.com",
      "follower_count": "345000",
      "engagement_rate": "3.5",
      "niche": "Travel",
      "contact_status": "contacted",
      "stage": "2",
      "outreach_method": "email",
      "agreed_rate": "700",
      "notes": "Hiking and camping content. Good for outdoor gear.",
      "custom": {}
    },
    {
      "id": "mock-12",
      "handle": "@gaming_leo",
      "platform": "youtube",
      "full_name": "Leo Martinez",
      "email": "leo@gaming.com",
      "follower_count": "2340000",
      "engagement_rate": "3.1",
      "niche": "Gaming",
      "contact_status": "interested",
      "stage": "3",
      "outreach_method": "email",
      "agreed_rate": "3000",
      "notes": "Fortnite streamer. Large following.",
      "custom": {}
    },
    {
      "id": "mock-13",
      "handle": "@wellness_sarah",
      "platform": "instagram",
      "full_name": "Sarah Johnson",
      "email": "sarah@wellness.com",
      "follower_count": "187000",
      "engagement_rate": "4.9",
      "niche": "Wellness",
      "contact_status": "agreed",
      "stage": "4",
      "outreach_method": "email",
      "agreed_rate": "600",
      "notes": "Yoga and meditation. Signed for wellness app.",
      "custom": {}
    },
    {
      "id": "mock-14",
      "handle": "@skincare_dr",
      "platform": "tiktok",
      "full_name": "Dr. Emily Chen",
      "email": "emily@derm.com",
      "follower_count": "456000",
      "engagement_rate": "5.5",
      "niche": "Skincare",
      "contact_status": "contacted",
      "stage": "2",
      "outreach_method": "dm",
      "agreed_rate": "850",
      "notes": "Dermatologist. Credible skincare advice.",
      "custom": {}
    },
    {
      "id": "mock-15",
      "handle": "@comedy_dave",
      "platform": "tiktok",
      "full_name": "Dave Miller",
      "email": "dave@comedy.com",
      "follower_count": "3450000",
      "engagement_rate": "8.2",
      "niche": "Comedy",
      "contact_status": "not_contacted",
      "stage": "1",
      "outreach_method": "",
      "agreed_rate": "",
      "notes": "Sketch comedy. Viral potential.",
      "custom": {}
    },
    {
      "id": "mock-16",
      "handle": "@home_reno_anna",
      "platform": "instagram",
      "full_name": "Anna Garcia",
      "email": "anna@home.com",
      "follower_count": "234000",
      "engagement_rate": "3.9",
      "niche": "Home Decor",
      "contact_status": "interested",
      "stage": "2",
      "outreach_method": "email",
      "agreed_rate": "550",
      "notes": "DIY and renovation projects.",
      "custom": {}
    },
    {
      "id": "mock-17",
      "handle": "@fitness_coach",
      "platform": "youtube",
      "full_name": "Mike Roberts",
      "email": "mike@fitness.com",
      "follower_count": "567000",
      "engagement_rate": "4.2",
      "niche": "Fitness",
      "contact_status": "agreed",
      "stage": "4",
      "outreach_method": "email",
      "agreed_rate": "1100",
      "notes": "Personal trainer. Workout programs.",
      "custom": {}
    },
    {
      "id": "mock-18",
      "handle": "@book_lover",
      "platform": "instagram",
      "full_name": "Rachel Green",
      "email": "rachel@books.com",
      "follower_count": "89000",
      "engagement_rate": "6.1",
      "niche": "Books",
      "contact_status": "contacted",
      "stage": "2",
      "outreach_method": "dm",
      "agreed_rate": "250",
      "notes": "Book reviews and recommendations.",
      "custom": {}
    },
    {
      "id": "mock-19",
      "handle": "@tech_review",
      "platform": "youtube",
      "full_name": "Chris Evans",
      "email": "chris@tech.com",
      "follower_count": "678000",
      "engagement_rate": "3.7",
      "niche": "Technology",
      "contact_status": "interested",
      "stage": "3",
      "outreach_method": "email",
      "agreed_rate": "1300",
      "notes": "Gadget reviews. Good for electronics.",
      "custom": {}
    },
    {
      "id": "mock-20",
      "handle": "@sustainable_life",
      "platform": "instagram",
      "full_name": "Laura White",
      "email": "laura@eco.com",
      "follower_count": "123000",
      "engagement_rate": "4.8",
      "niche": "Sustainability",
      "contact_status": "contacted",
      "stage": "1",
      "outreach_method": "dm",
      "agreed_rate": "400",
      "notes": "Zero waste living. Eco-friendly products.",
      "custom": {}
    },
    {
      "id": "mock-21",
      "handle": "@dance_moves",
      "platform": "tiktok",
      "full_name": "Carlos Mendez",
      "email": "carlos@dance.com",
      "follower_count": "2300000",
      "engagement_rate": "9.1",
      "niche": "Dance",
      "contact_status": "not_contacted",
      "stage": "1",
      "outreach_method": "",
      "agreed_rate": "",
      "notes": "Choreography and dance trends.",
      "custom": {}
    },
    {
      "id": "mock-22",
      "handle": "@art_by_maya",
      "platform": "instagram",
      "full_name": "Maya Patel",
      "email": "maya@art.com",
      "follower_count": "156000",
      "engagement_rate": "5.3",
      "niche": "Art",
      "contact_status": "interested",
      "stage": "2",
      "outreach_method": "email",
      "agreed_rate": "380",
      "notes": "Digital art and illustrations.",
      "custom": {}
    },
    {
      "id": "mock-23",
      "handle": "@cooking_with_paul",
      "platform": "youtube",
      "full_name": "Paul Johnson",
      "email": "paul@cooking.com",
      "follower_count": "345000",
      "engagement_rate": "4.4",
      "niche": "Food",
      "contact_status": "agreed",
      "stage": "4",
      "outreach_method": "email",
      "agreed_rate": "750",
      "notes": "Recipe tutorials. Signed for kitchenware campaign.",
      "custom": {}
    },
    {
      "id": "mock-24",
      "handle": "@photography_ian",
      "platform": "instagram",
      "full_name": "Ian Foster",
      "email": "ian@photo.com",
      "follower_count": "289000",
      "engagement_rate": "3.2",
      "niche": "Photography",
      "contact_status": "contacted",
      "stage": "2",
      "outreach_method": "dm",
      "agreed_rate": "600",
      "notes": "Landscape photography. Great for camera gear.",
      "custom": {}
    },
    {
      "id": "mock-25",
      "handle": "@business_mind",
      "platform": "twitter",
      "full_name": "Kevin Zhang",
      "email": "kevin@business.com",
      "follower_count": "78000",
      "engagement_rate": "2.9",
      "niche": "Business",
      "contact_status": "interested",
      "stage": "2",
      "outreach_method": "dm",
      "agreed_rate": "350",
      "notes": "Entrepreneurship tips. Good for B2B.",
      "custom": {}
    },
    {
      "id": "mock-26",
      "handle": "@nail_art_emma",
      "platform": "instagram",
      "full_name": "Emma Watson",
      "email": "emma@nails.com",
      "follower_count": "345000",
      "engagement_rate": "6.7",
      "niche": "Beauty",
      "contact_status": "contacted",
      "stage": "3",
      "outreach_method": "email",
      "agreed_rate": "480",
      "notes": "Nail art tutorials. High engagement.",
      "custom": {}
    },
    {
      "id": "mock-27",
      "handle": "@fishing_adventures",
      "platform": "youtube",
      "full_name": "Tom Fisher",
      "email": "tom@fishing.com",
      "follower_count": "234000",
      "engagement_rate": "3.8",
      "niche": "Outdoor",
      "contact_status": "not_contacted",
      "stage": "1",
      "outreach_method": "",
      "agreed_rate": "",
      "notes": "Fishing and outdoor gear.",
      "custom": {}
    },
    {
      "id": "mock-28",
      "handle": "@psychology_tips",
      "platform": "tiktok",
      "full_name": "Dr. Sarah Kim",
      "email": "sarah@psych.com",
      "follower_count": "567000",
      "engagement_rate": "5.9",
      "niche": "Psychology",
      "contact_status": "interested",
      "stage": "2",
      "outreach_method": "dm",
      "agreed_rate": "720",
      "notes": "Mental health awareness. Credible source.",
      "custom": {}
    },
    {
      "id": "mock-29",
      "handle": "@luxury_living",
      "platform": "instagram",
      "full_name": "Victoria Chen",
      "email": "victoria@luxury.com",
      "follower_count": "1234000",
      "engagement_rate": "2.5",
      "niche": "Lifestyle",
      "contact_status": "agreed",
      "stage": "4",
      "outreach_method": "email",
      "agreed_rate": "3200",
      "notes": "Luxury lifestyle content. Signed for high-end brand.",
      "custom": {}
    },
    {
      "id": "mock-30",
      "handle": "@cycling_ben",
      "platform": "instagram",
      "full_name": "Ben Taylor",
      "email": "ben@cycling.com",
      "follower_count": "89000",
      "engagement_rate": "4.1",
      "niche": "Sports",
      "contact_status": "contacted",
      "stage": "1",
      "outreach_method": "dm",
      "agreed_rate": "280",
      "notes": "Mountain biking content.",
      "custom": {}
    },
    {
      "id": "mock-31",
      "handle": "@coding_ninja",
      "platform": "youtube",
      "full_name": "Alex Rivera",
      "email": "alex@coding.com",
      "follower_count": "456000",
      "engagement_rate": "3.3",
      "niche": "Technology",
      "contact_status": "interested",
      "stage": "2",
      "outreach_method": "email",
      "agreed_rate": "950",
      "notes": "Programming tutorials. Good for developer tools.",
      "custom": {}
    },
    {
      "id": "mock-32",
      "handle": "@makeup_artist",
      "platform": "instagram",
      "full_name": "Linda Zhao",
      "email": "linda@makeup.com",
      "follower_count": "789000",
      "engagement_rate": "4.6",
      "niche": "Beauty",
      "contact_status": "contacted",
      "stage": "3",
      "outreach_method": "dm",
      "agreed_rate": "1100",
      "notes": "Professional makeup artist. Celebrity clients.",
      "custom": {}
    },
    {
      "id": "mock-33",
      "handle": "@plant_mom",
      "platform": "instagram",
      "full_name": "Olivia Martinez",
      "email": "olivia@plants.com",
      "follower_count": "167000",
      "engagement_rate": "5.2",
      "niche": "Gardening",
      "contact_status": "agreed",
      "stage": "4",
      "outreach_method": "email",
      "agreed_rate": "420",
      "notes": "Plant care tips. Signed for gardening tools.",
      "custom": {}
    },
    {
      "id": "mock-34",
      "handle": "@esports_pro",
      "platform": "youtube",
      "full_name": "Marcus Lee",
      "email": "marcus@gaming.com",
      "follower_count": "2345000",
      "engagement_rate": "7.8",
      "niche": "Gaming",
      "contact_status": "not_contacted",
      "stage": "1",
      "outreach_method": "",
      "agreed_rate": "",
      "notes": "Professional gamer. Large following.",
      "custom": {}
    },
    {
      "id": "mock-35",
      "handle": "@french_cuisine",
      "platform": "tiktok",
      "full_name": "Pierre Dubois",
      "email": "pierre@food.com",
      "follower_count": "345000",
      "engagement_rate": "4.9",
      "niche": "Food",
      "contact_status": "interested",
      "stage": "2",
      "outreach_method": "email",
      "agreed_rate": "680",
      "notes": "French cooking tutorials.",
      "custom": {}
    },
    {
      "id": "mock-36",
      "handle": "@yoga_with_sofia",
      "platform": "youtube",
      "full_name": "Sofia Rodriguez",
      "email": "sofia@yoga.com",
      "follower_count": "678000",
      "engagement_rate": "3.6",
      "niche": "Wellness",
      "contact_status": "contacted",
      "stage": "2",
      "outreach_method": "dm",
      "agreed_rate": "880",
      "notes": "Yoga instructor. Good for activewear.",
      "custom": {}
    },
    {
      "id": "mock-37",
      "handle": "@marketing_guru",
      "platform": "twitter",
      "full_name": "David Chen",
      "email": "david@marketing.com",
      "follower_count": "123000",
      "engagement_rate": "3.4",
      "niche": "Marketing",
      "contact_status": "interested",
      "stage": "2",
      "outreach_method": "dm",
      "agreed_rate": "520",
      "notes": "Digital marketing tips. B2B potential.",
      "custom": {}
    },
    {
      "id": "mock-38",
      "handle": "@sports_car",
      "platform": "instagram",
      "full_name": "James Wilson",
      "email": "james@cars.com",
      "follower_count": "890000",
      "engagement_rate": "2.8",
      "niche": "Automotive",
      "contact_status": "agreed",
      "stage": "4",
      "outreach_method": "email",
      "agreed_rate": "2100",
      "notes": "Luxury car reviews. Signed for automotive brand.",
      "custom": {}
    },
    {
      "id": "mock-39",
      "handle": "@skincare_routine",
      "platform": "tiktok",
      "full_name": "Nina Patel",
      "email": "nina@skincare.com",
      "follower_count": "456000",
      "engagement_rate": "6.4",
      "niche": "Skincare",
      "contact_status": "contacted",
      "stage": "3",
      "outreach_method": "dm",
      "agreed_rate": "750",
      "notes": "K-beauty routines. High engagement.",
      "custom": {}
    },
    {
      "id": "mock-40",
      "handle": "@woodworking_art",
      "platform": "youtube",
      "full_name": "Michael Scott",
      "email": "michael@wood.com",
      "follower_count": "234000",
      "engagement_rate": "4.3",
      "niche": "DIY",
      "contact_status": "interested",
      "stage": "2",
      "outreach_method": "email",
      "agreed_rate": "590",
      "notes": "Woodworking projects. Good for tools.",
      "custom": {}
    },
    {
      "id": "mock-41",
      "handle": "@fashion_edit",
      "platform": "instagram",
      "full_name": "Isabella Cruz",
      "email": "isa@fashion.com",
      "follower_count": "567000",
      "engagement_rate": "4.7",
      "niche": "Fashion",
      "contact_status": "not_contacted",
      "stage": "1",
      "outreach_method": "",
      "agreed_rate": "",
      "notes": "Street style content.",
      "custom": {}
    },
    {
      "id": "mock-42",
      "handle": "@fitness_nutrition",
      "platform": "tiktok",
      "full_name": "Dr. James Park",
      "email": "james@nutrition.com",
      "follower_count": "789000",
      "engagement_rate": "5.6",
      "niche": "Fitness",
      "contact_status": "contacted",
      "stage": "2",
      "outreach_method": "dm",
      "agreed_rate": "980",
      "notes": "Nutrition advice. Credible source.",
      "custom": {}
    },
    {
      "id": "mock-43",
      "handle": "@digital_art",
      "platform": "instagram",
      "full_name": "Sophia Chen",
      "email": "sophia@art.com",
      "follower_count": "156000",
      "engagement_rate": "5.8",
      "niche": "Art",
      "contact_status": "interested",
      "stage": "2",
      "outreach_method": "email",
      "agreed_rate": "450",
      "notes": "Digital illustrations.",
      "custom": {}
    },
    {
      "id": "mock-44",
      "handle": "@outdoor_adventure",
      "platform": "youtube",
      "full_name": "Ryan Cooper",
      "email": "ryan@outdoor.com",
      "follower_count": "345000",
      "engagement_rate": "4.1",
      "niche": "Travel",
      "contact_status": "agreed",
      "stage": "3",
      "outreach_method": "email",
      "agreed_rate": "820",
      "notes": "Camping and hiking content. Signed for outdoor brand.",
      "custom": {}
    },
    {
      "id": "mock-45",
      "handle": "@parenting_hacks",
      "platform": "instagram",
      "full_name": "Emily Davis",
      "email": "emily@parenting.com",
      "follower_count": "278000",
      "engagement_rate": "4.9",
      "niche": "Parenting",
      "contact_status": "contacted",
      "stage": "2",
      "outreach_method": "dm",
      "agreed_rate": "530",
      "notes": "Parenting tips and hacks.",
      "custom": {}
    },
    {
      "id": "mock-46",
      "handle": "@astro_photography",
      "platform": "instagram",
      "full_name": "Chris Evans",
      "email": "chris@astro.com",
      "follower_count": "123000",
      "engagement_rate": "3.9",
      "niche": "Photography",
      "contact_status": "interested",
      "stage": "1",
      "outreach_method": "dm",
      "agreed_rate": "380",
      "notes": "Astrophotography content.",
      "custom": {}
    },
    {
      "id": "mock-47",
      "handle": "@street_food",
      "platform": "tiktok",
      "full_name": "Carlos Mendez",
      "email": "carlos@food.com",
      "follower_count": "456000",
      "engagement_rate": "6.2",
      "niche": "Food",
      "contact_status": "contacted",
      "stage": "2",
      "outreach_method": "email",
      "agreed_rate": "670",
      "notes": "Street food reviews. Good for food brands.",
      "custom": {}
    },
    {
      "id": "mock-48",
      "handle": "@meditation_guide",
      "platform": "youtube",
      "full_name": "Lily Zhang",
      "email": "lily@meditation.com",
      "follower_count": "234000",
      "engagement_rate": "4.5",
      "niche": "Wellness",
      "contact_status": "agreed",
      "stage": "4",
      "outreach_method": "email",
      "agreed_rate": "610",
      "notes": "Meditation and mindfulness. Signed for wellness app.",
      "custom": {}
    },
    {
      "id": "mock-49",
      "handle": "@data_science",
      "platform": "twitter",
      "full_name": "Dr. Maria Garcia",
      "email": "maria@data.com",
      "follower_count": "89000",
      "engagement_rate": "2.9",
      "niche": "Technology",
      "contact_status": "interested",
      "stage": "2",
      "outreach_method": "dm",
      "agreed_rate": "420",
      "notes": "Data science insights. Good for tech brands.",
      "custom": {}
    },
    {
      "id": "mock-50",
      "handle": "@vintage_style",
      "platform": "instagram",
      "full_name": "Emma Watson",
      "email": "emma@vintage.com",
      "follower_count": "145000",
      "engagement_rate": "5.1",
      "niche": "Fashion",
      "contact_status": "contacted",
      "stage": "2",
      "outreach_method": "dm",
      "agreed_rate": "480",
      "notes": "Vintage fashion content. High engagement.",
      "custom": {}
    },
    {
      "id": "mock-51",
      "handle": "@esports_analyst",
      "platform": "youtube",
      "full_name": "Jonathan Kim",
      "email": "jonathan@esports.com",
      "follower_count": "567000",
      "engagement_rate": "4.8",
      "niche": "Gaming",
      "contact_status": "not_contacted",
      "stage": "1",
      "outreach_method": "",
      "agreed_rate": "",
      "notes": "Esports analysis. Good for gaming brands.",
      "custom": {}
    },
    {
      "id": "mock-52",
      "handle": "@sustainable_fashion",
      "platform": "instagram",
      "full_name": "Grace Lee",
      "email": "grace@eco-fashion.com",
      "follower_count": "198000",
      "engagement_rate": "5.5",
      "niche": "Fashion",
      "contact_status": "interested",
      "stage": "2",
      "outreach_method": "email",
      "agreed_rate": "560",
      "notes": "Eco-friendly fashion. Good for sustainable brands.",
      "custom": {}
    }
  ]
}